sphinx_ustack_theme/__init__.py
sphinx_ustack_theme/breadcrumbs.html
sphinx_ustack_theme/footer.html
sphinx_ustack_theme/layout.html
sphinx_ustack_theme/search.html
sphinx_ustack_theme/searchbox.html
sphinx_ustack_theme/theme.conf
sphinx_ustack_theme/versions.html
sphinx_ustack_theme/static/css/badge_only.css
sphinx_ustack_theme/static/css/theme.css
sphinx_ustack_theme/static/fonts/fontawesome-webfont.eot
sphinx_ustack_theme/static/fonts/fontawesome-webfont.svg
sphinx_ustack_theme/static/fonts/fontawesome-webfont.ttf
sphinx_ustack_theme/static/fonts/fontawesome-webfont.woff
sphinx_ustack_theme/static/fonts/fontawesome-webfont.woff2
sphinx_ustack_theme/static/fonts/Lato/lato-bold.eot
sphinx_ustack_theme/static/fonts/Lato/lato-bold.ttf
sphinx_ustack_theme/static/fonts/Lato/lato-bold.woff
sphinx_ustack_theme/static/fonts/Lato/lato-bold.woff2
sphinx_ustack_theme/static/fonts/Lato/lato-bolditalic.eot
sphinx_ustack_theme/static/fonts/Lato/lato-bolditalic.ttf
sphinx_ustack_theme/static/fonts/Lato/lato-bolditalic.woff
sphinx_ustack_theme/static/fonts/Lato/lato-bolditalic.woff2
sphinx_ustack_theme/static/fonts/Lato/lato-italic.eot
sphinx_ustack_theme/static/fonts/Lato/lato-italic.ttf
sphinx_ustack_theme/static/fonts/Lato/lato-italic.woff
sphinx_ustack_theme/static/fonts/Lato/lato-italic.woff2
sphinx_ustack_theme/static/fonts/Lato/lato-regular.eot
sphinx_ustack_theme/static/fonts/Lato/lato-regular.ttf
sphinx_ustack_theme/static/fonts/Lato/lato-regular.woff
sphinx_ustack_theme/static/fonts/Lato/lato-regular.woff2
sphinx_ustack_theme/static/fonts/RobotoSlab/roboto-slab-v7-bold.eot
sphinx_ustack_theme/static/fonts/RobotoSlab/roboto-slab-v7-bold.ttf
sphinx_ustack_theme/static/fonts/RobotoSlab/roboto-slab-v7-bold.woff
sphinx_ustack_theme/static/fonts/RobotoSlab/roboto-slab-v7-bold.woff2
sphinx_ustack_theme/static/fonts/RobotoSlab/roboto-slab-v7-regular.eot
sphinx_ustack_theme/static/fonts/RobotoSlab/roboto-slab-v7-regular.ttf
sphinx_ustack_theme-1.0.0.dist-info/METADATA
sphinx_ustack_theme-1.0.0.dist-info/RECORD
sphinx_ustack_theme-1.0.0.dist-info/WHEEL
sphinx_ustack_theme-1.0.0.dist-info/entry_points.txt
sphinx_ustack_theme-1.0.0.dist-info/top_level.txt
